<?xml version="1.0" encoding="UTF-8"?>
<fixer>
	<element>
		<notation>解决302重定向页面后无法退出的问题</notation>
		<name>awale inject</name>
		<whiteUrl>
			<url>http://4006024680.com</url>
		</whiteUrl>
		<blackUrl>
		</blackUrl>
		<position>bottom</position>
		<type>js</type>
		<file>js_exit_routerPage.js</file>
	</element>
	<element>
		<notation>增加js小键盘功能</notation>
		<name>inject js input method</name>
		<whiteUrl>
            <url>search.html</url>
		</whiteUrl>
		<blackUrl>
		</blackUrl>
		<position>bottom</position>
		<type>js</type>
		<file>js_tclime_keyboard_1080.js</file>
	</element>
	<element>
		<notation>voice control</notation>
		<name>voice control</name>
		<whiteUrl>
		</whiteUrl>
		<blackUrl>
		</blackUrl>
		<position>top</position>
		<type>js</type>
		<file>js_voice_control_.js</file>
	</element>
</fixer>